txffpAssistant/__init__.py
txffpAssistant/__main__.py
txffpAssistant/archive.py
txffpAssistant/cli.py
txffpAssistant/component.py
txffpAssistant/decorators.py
txffpAssistant/exceptions.py
txffpAssistant/logger.py
txffpAssistant/pdf.py
txffpAssistant/handler/__init__.py
txffpAssistant/handler/auth.py
txffpAssistant/handler/base.py
txffpAssistant/handler/generic.py
txffpAssistant-1.1.0.dist-info/METADATA
txffpAssistant-1.1.0.dist-info/RECORD
txffpAssistant-1.1.0.dist-info/WHEEL
txffpAssistant-1.1.0.dist-info/entry_points.txt
txffpAssistant-1.1.0.dist-info/top_level.txt
