Metadata-Version: 2.1
Name: txffpAssistant
Version: 1.1.0
Summary: 为解决某票根网反人类设计的一款助手工具
Home-page: https://github.com/Kairu-Madigan/txffpAssistant
Author: Kyle
Author-email: kairu_madigan@yahoo.co.jp
License: GNU
Platform: any
Classifier: Intended Audience :: Other Audience
Classifier: License :: OSI Approved :: GNU General Public License v3 (GPLv3)
Classifier: Natural Language :: Chinese (Simplified)
Classifier: Operating System :: OS Independent
Classifier: Programming Language :: Python
Classifier: Programming Language :: Python :: 3.4
Classifier: Programming Language :: Python :: 3.5
Classifier: Programming Language :: Python :: 3.6
Classifier: Programming Language :: Python :: 3.7
Requires-Python: >=3.4
Requires-Dist: lxml (>=4.2.3)
Requires-Dist: requests (>=2.19.1)
Requires-Dist: PyPDF2 (>=1.26.0)
Requires-Dist: filetype (>=1.0.1)
Requires-Dist: prettytable (>=0.7.2)
Requires-Dist: python-dateutil (==2.7.3)
